adotestplan_to_pytestbdd/__init__.py
adotestplan_to_pytestbdd/ado_test_plan.py
adotestplan_to_pytestbdd/exceptions.py
adotestplan_to_pytestbdd-0.1.9.dist-info/LICENSE
adotestplan_to_pytestbdd-0.1.9.dist-info/METADATA
adotestplan_to_pytestbdd-0.1.9.dist-info/WHEEL
adotestplan_to_pytestbdd-0.1.9.dist-info/RECORD
