Metadata-Version: 2.1
Name: adotestplan-to-pytestbdd
Version: 0.1.9
Summary: Utility for translating AzureDevOps Test Plans to Gherkin Feature file and Pytest-BDD runners
Home-page: https://github.com/bissell-homecare-inc/adotestplan-to-pytestbdd
Keywords: ADO,AzureDevOps,BDD
Author: David VanKampen
Author-email: david.vankampen@bissell.com
Requires-Python: >=3.9,<4.0
Classifier: Development Status :: 3 - Alpha
Classifier: Intended Audience :: Developers
Classifier: License :: OSI Approved :: MIT License
Classifier: Programming Language :: Python :: 3
Classifier: Programming Language :: Python :: 3.9
Classifier: Programming Language :: Python :: 3.10
Classifier: Programming Language :: Python :: 3.11
Classifier: Programming Language :: Python :: 3.12
Classifier: Programming Language :: Python :: 3.8
Classifier: Topic :: Software Development :: Code Generators
Classifier: Topic :: Software Development :: Testing :: BDD
Classifier: Topic :: Utilities
Requires-Dist: azure-devops (>=7.1.0b4,<8.0.0)
Requires-Dist: beautifulsoup4 (>=4.12.3,<5.0.0)
Requires-Dist: gherlint (>=0.4.0,<0.5.0)
Requires-Dist: pydot (>=2.0.0,<3.0.0)
Requires-Dist: thefuzz (>=0.22.1,<0.23.0)
Requires-Dist: timebudget (>=0.7.1,<0.8.0)
Project-URL: Bug Tracker, https://github.com/bissell-homecare-inc/adotestplan-to-pytestbdd/issues
Project-URL: Repository, https://github.com/bissell-homecare-inc/adotestplan-to-pytestbdd
